{
	"pages": [ 
		{
			"path": "pages/index/index",
			"style": {
				// "navigationBarTitleText": "uni-app"
			}
		},
		{
			"path": "pages/xlsx/index",
			"style": {
				// "navigationBarTitleText": "uni-app"
			}
		}
	],
	"globalStyle": {
		"navigationStyle":"custom",
		"navigationBarTextStyle": "black",
		"navigationBarTitleText": "娇娇专属",
		"navigationBarBackgroundColor": "#F8F8F8",
		"backgroundColor": "#F8F8F8"
	},
	"easycom": {
		"autoscan": true,
		"custom": {  
	        "^u-(.*)": "uview-plus/components/u-$1/u-$1.vue" 
		}
	}
}
